{
  "mappings": [
    {
      "type": "file",
      "from": "src/VirtualDofMatrix.App/bin/Release/net8.0-windows/win-x64/publish/VirtualDofMatrix.App.exe",
      "to": "VirtualDofMatrix.App.exe"
    },
    {
      "type": "directory",
      "from": "DOF",
      "to": "DOF"
    },
    {
      "type": "file",
      "from": "examples/settings.sample.json",
      "to": "examples/settings.sample.json"
    },
    {
      "type": "file",
      "from": "docs/instructions.html",
      "to": "docs/instructions.html"
    }
  ]
}
